city_of_saskatoon_auth/__init__.py
city_of_saskatoon_auth/cos_login.py
city_of_saskatoon_auth/exceptions.py
city_of_saskatoon_auth/parse.py
city_of_saskatoon_auth/session.py
city_of_saskatoon_auth/smart_util_login.py
city_of_saskatoon_auth-0.0.3.dist-info/METADATA
city_of_saskatoon_auth-0.0.3.dist-info/WHEEL
city_of_saskatoon_auth-0.0.3.dist-info/licenses/LICENSE
city_of_saskatoon_auth-0.0.3.dist-info/RECORD
