Metadata-Version: 2.1
Name: city_of_saskatoon_auth
Version: 0.0.3
Summary: An unofficial Python module for authenticating with the City of Saskatoon website
Project-URL: Homepage, https://github.com/evansalter/city-of-saskatoon-auth
Project-URL: Bug Tracker, https://github.com/evansalter/city-of-saskatoon-auth/issues
Author-email: Evan Salter <hi@evansalter.com>
License: MIT License
License-File: LICENSE
Classifier: License :: OSI Approved :: MIT License
Classifier: Operating System :: OS Independent
Classifier: Programming Language :: Python :: 3
Requires-Python: >=3.7
Requires-Dist: requests
